kares/Practical_1.txt
kares/Practical_2.txt
kares/Practical_3.txt
kares/Practical_4.txt
kares/Practical_5.txt
kares/Practical_6.txt
kares/Practical_7.txt
kares/Practical_8.txt
kares/Practical_9.txt
kares/__init__.py
kares-0.12.dist-info/METADATA
kares-0.12.dist-info/WHEEL
kares-0.12.dist-info/top_level.txt
kares-0.12.dist-info/RECORD
